pg_jsonb_flattener.py
pg_jsonb_flattener-0.2.0.dist-info/LICENSE.txt
pg_jsonb_flattener-0.2.0.dist-info/METADATA
pg_jsonb_flattener-0.2.0.dist-info/WHEEL
pg_jsonb_flattener-0.2.0.dist-info/top_level.txt
pg_jsonb_flattener-0.2.0.dist-info/RECORD
