Metadata-Version: 2.1
Name: pg-jsonb-flattener
Version: 0.2.0
Summary: JSONB data flattener for Postgresl
Home-page: https://gitlab.com/askorski/pg_jsonb_flattener
Author: Anthony SKORSKI
Author-email: skorski.anthony+pg_jsonb_flattener@gmail.com
License: MIT
Keywords: postgresql,jsonb,sqlalchemy
Platform: UNKNOWN
Classifier: Development Status :: 3 - Alpha
Classifier: Programming Language :: Python :: 2
Classifier: Intended Audience :: Developers
Classifier: License :: OSI Approved :: MIT License
Classifier: Operating System :: OS Independent
Classifier: Programming Language :: Python :: 3
Classifier: Topic :: Database
Requires-Dist: psycopg2
Requires-Dist: sqlalchemy
Provides-Extra: dev
Requires-Dist: flake8 ; extra == 'dev'
Requires-Dist: flake8-html ; extra == 'dev'
Requires-Dist: sphinx ; extra == 'dev'
Requires-Dist: sphinx-rtd-theme ; extra == 'dev'
Requires-Dist: coverage ; extra == 'dev'
Requires-Dist: pytest ; extra == 'dev'
Requires-Dist: pytest-cov ; extra == 'dev'
Requires-Dist: pytest-html ; extra == 'dev'
Provides-Extra: test
Requires-Dist: coverage ; extra == 'test'
Requires-Dist: pytest ; extra == 'test'
Requires-Dist: pytest-cov ; extra == 'test'
Requires-Dist: pytest-html ; extra == 'test'
